{"welcome":{"id":"welcome","title":"Welcome","factor":1,"bg":"page1.png","bg-color":"#ffd","bg-repeat":"repeat","position":{"left":100,"top":350},"weight":1,"texts":[{"id":"text1","title":"Welcome to Dreamflight!","text":"Welcome to Dreamflight. Dreamflight is just a random word that came into my mind!!!","text_bg":"splash4.png","position":{"left":100,"top":350},"dimension":{"width":300,"height":350}}],"objects":[{"id":"cloud1","img":"cloud.png","position":{"left":430,"top":25},"factor":0.6,"z-index":2},{"id":"baloon1","img":"baloon.png","position":{"left":500,"top":300},"factor":-1.5,"z-index":4},{"id":"sun1","img":"sun.png","position":{"left":600,"top":50},"factor":0.8,"z-index":1}]},"about":{"id":"about","title":"About me","text":"Its already too late, I am so sleepy. Good night Sunila Maharjan ;)","text_bg":"splash1.png","position":{"left":655,"top":350},"factor":1,"bg":"page2.png","bg-color":"#333","bg-repeat":"repeat","weight":2,"texts":[{"id":"text1","title":"About Me!","text":"Welcome to Dreamflight. Dreamflight is just a random word that came into my mind!!!","text_bg":"splash4.png","position":{"left":100,"top":350},"dimension":{"width":300,"height":350}}],"objects":[{"id":"cloud2","img":"cloud1.png","position":{"left":260,"top":75},"factor":0.6,"z-index":3},{"id":"baloon2","img":"baloon.png","position":{"left":0,"top":470},"factor":-1.5,"z-index":4},{"id":"moon2","img":"moon.png","position":{"left":55,"top":40},"factor":0.8,"z-index":2},{"id":"stars","img":"stars.png","position":{"left":55,"top":40},"factor":0.95,"z-index":1}]},"contact":{"id":"contact","title":"Contact","text":"\r\n <form action=\"\">\r\n   <div><label for=\"\">Name<\/label><input type=\"text\" \/><\/div>\r\n   <div><label for=\"\">Email<\/label><input type=\"text\" \/><\/div>\r\n   <div><label for=\"\">Subject<\/label><input type=\"text\" \/><\/div>\r\n   <div><label for=\"\">Message<\/label><textarea><\/textarea><\/div>\r\n <\/form> \r\n","position":{"left":100,"top":150},"factor":1,"text_bg":"splash2.png","bg":"page3.png","bg-repeat":"repeat","bg-color":"#eee","weight":0,"texts":[{"id":"Contact","title":"Contact Me!","text":"\r\n <form action=\"\">\r\n   <div><label for=\"\">Name<\/label><input type=\"text\" \/><\/div>\r\n   <div><label for=\"\">Email<\/label><input type=\"text\" \/><\/div>\r\n   <div><label for=\"\">Subject<\/label><input type=\"text\" \/><\/div>\r\n   <div><label for=\"\">Message<\/label><textarea><\/textarea><\/div>\r\n <\/form> \r\n","text_bg":"splash4.png","position":{"left":100,"top":350},"dimension":{"width":300,"height":350}}],"objects":[{"id":"cloud3","img":"cloud.png","position":{"left":650,"top":175},"factor":0.6,"z-index":0},{"id":"baloon3","img":"baloon.png","position":{"left":400,"top":175},"factor":-0.5,"z-index":2},{"id":"mailbox","img":"mailbox.png","position":{"left":700,"top":375},"factor":0,"z-index":2}]}}